sphobjinv/__init__.py
sphobjinv/__main__.py
sphobjinv/data.py
sphobjinv/enum.py
sphobjinv/error.py
sphobjinv/fileops.py
sphobjinv/inventory.py
sphobjinv/re.py
sphobjinv/schema.py
sphobjinv/version.py
sphobjinv/zlib.py
sphobjinv/_vendored/__init__.py
sphobjinv/_vendored/fuzzywuzzy/__init__.py
sphobjinv/_vendored/fuzzywuzzy/fuzz.py
sphobjinv/_vendored/fuzzywuzzy/process.py
sphobjinv/_vendored/fuzzywuzzy/tests.py
sphobjinv/_vendored/fuzzywuzzy/utils.py
sphobjinv/cli/__init__.py
sphobjinv/cli/convert.py
sphobjinv/cli/core.py
sphobjinv/cli/load.py
sphobjinv/cli/parser.py
sphobjinv/cli/paths.py
sphobjinv/cli/suggest.py
sphobjinv/cli/ui.py
sphobjinv/cli/write.py
sphobjinv-2.3.1.3.dist-info/licenses/LICENSE.txt
sphobjinv-2.3.1.3.dist-info/METADATA
sphobjinv-2.3.1.3.dist-info/WHEEL
sphobjinv-2.3.1.3.dist-info/entry_points.txt
sphobjinv-2.3.1.3.dist-info/top_level.txt
sphobjinv-2.3.1.3.dist-info/RECORD
