Metadata-Version: 2.4
Name: sphobjinv
Version: 2.3.1.3
Summary: Sphinx objects.inv Inspection/Manipulation Tool
Author-email: Brian Skinn <brian.skinn@gmail.com>
License: MIT License
Project-URL: Homepage, https://github.com/bskinn/sphobjinv
Project-URL: Changelog, https://github.com/bskinn/sphobjinv/blob/main/CHANGELOG.md
Project-URL: Docs, https://sphobjinv.readthedocs.io/en/stable/
Project-URL: Thank, https://fosstodon.org/@btskinn
Project-URL: Donate, https://github.com/sponsors/bskinn
Keywords: sphinx,sphinx-doc,inventory,manager,inspector
Platform: any
Classifier: License :: OSI Approved
Classifier: License :: OSI Approved :: MIT License
Classifier: Natural Language :: English
Classifier: Environment :: Console
Classifier: Framework :: Sphinx
Classifier: Intended Audience :: Developers
Classifier: Operating System :: OS Independent
Classifier: Programming Language :: Python
Classifier: Programming Language :: Python :: 3
Classifier: Programming Language :: Python :: 3 :: Only
Classifier: Programming Language :: Python :: 3.9
Classifier: Programming Language :: Python :: 3.10
Classifier: Programming Language :: Python :: 3.11
Classifier: Programming Language :: Python :: 3.12
Classifier: Programming Language :: Python :: 3.13
Classifier: Topic :: Documentation
Classifier: Topic :: Documentation :: Sphinx
Classifier: Topic :: Software Development
Classifier: Topic :: Software Development :: Documentation
Classifier: Topic :: Utilities
Classifier: Development Status :: 5 - Production/Stable
Requires-Python: >=3.9
License-File: LICENSE.txt
Requires-Dist: attrs>=19.2
Requires-Dist: certifi
Requires-Dist: jsonschema>=3.0
Dynamic: description
Dynamic: description-content-type
Dynamic: license-file
